lightningrobot_cli/__init__.py
lightningrobot_cli/create.py
lightningrobot_cli/install.py
lightningrobot_cli/runbot.py
lightningrobot_cli/xxx.ico
lightningrobot_cli-0.1.9.dist-info/entry_points.txt
lightningrobot_cli-0.1.9.dist-info/LICENSE
lightningrobot_cli-0.1.9.dist-info/METADATA
lightningrobot_cli-0.1.9.dist-info/WHEEL
lightningrobot_cli-0.1.9.dist-info/RECORD
